design.sv
module sync_fifo #(
    parameter DATA_WIDTH = 8,
    parameter DEPTH = 16,
    parameter ADDR_WIDTH = 4    // log2(DEPTH)
)(
    input                       clk,
    input                       rst,

    input                       wr_en,
    input                       rd_en,
    input  [DATA_WIDTH-1:0]     din,

    output reg [DATA_WIDTH-1:0] dout,
    output                      full,
    output                      empty
);

    // FIFO Memory
    reg [DATA_WIDTH-1:0] mem [0:DEPTH-1];

    // Read and Write pointers
    reg [ADDR_WIDTH-1:0] wr_ptr;
    reg [ADDR_WIDTH-1:0] rd_ptr;

    // Counter to track number of elements
    reg [ADDR_WIDTH:0] count;

    // Write operation
    always @(posedge clk or posedge rst) begin
        if (rst) begin
            wr_ptr <= 0;
        end
        else if (wr_en && !full) begin
            mem[wr_ptr] <= din;
            wr_ptr <= wr_ptr + 1;
        end
    end

    // Read operation
    always @(posedge clk or posedge rst) begin
        if (rst) begin
            rd_ptr <= 0;
            dout <= 0;
        end
        else if (rd_en && !empty) begin
            dout <= mem[rd_ptr];
            rd_ptr <= rd_ptr + 1;
        end
    end

    // Count logic
    always @(posedge clk or posedge rst) begin
        if (rst) begin
            count <= 0;
        end
        else begin
            case ({wr_en && !full, rd_en && !empty})
                2'b10: count <= count + 1; // Write only
                2'b01: count <= count - 1; // Read only
                2'b11: count <= count;     // Simultaneous read & write
                default: count <= count;
            endcase
        end
    end

    // Status signals
    assign full  = (count == DEPTH);
    assign empty = (count == 0);

endmodule

testbench.sv
`timescale 1ns/1ps

module tb_sync_fifo;

    parameter DATA_WIDTH = 8;
    parameter DEPTH      = 16;
    parameter ADDR_WIDTH = 4;

    reg clk;
    reg rst;
    reg wr_en;
    reg rd_en;
    reg [DATA_WIDTH-1:0] din;

    wire [DATA_WIDTH-1:0] dout;
    wire full;
    wire empty;

    // Instantiate FIFO
    sync_fifo #(
        .DATA_WIDTH(DATA_WIDTH),
        .DEPTH(DEPTH),
        .ADDR_WIDTH(ADDR_WIDTH)
    ) uut (
        .clk(clk),
        .rst(rst),
        .wr_en(wr_en),
        .rd_en(rd_en),
        .din(din),
        .dout(dout),
        .full(full),
        .empty(empty)
    );

    // Clock generation (10 ns period)
    always #5 clk = ~clk;

    initial begin
        clk   = 0;
        rst   = 1;
        wr_en = 0;
        rd_en = 0;
        din   = 0;

        // Apply reset
        #20;
        rst = 0;

        
        // Write 5 values
        
        $display("\nWriting Data...");
        repeat(5) begin
            @(posedge clk);
            wr_en = 1;
            din = din + 8'h11;
        end

        @(posedge clk);
        wr_en = 0;

        
        // Read 5 values
        
        $display("\nReading Data...");
        repeat(5) begin
            @(posedge clk);
            rd_en = 1;
        end

        @(posedge clk);
        rd_en = 0;

        
        // Fill FIFO completely
        
        $display("\nFilling FIFO...");
        repeat(DEPTH) begin
            @(posedge clk);
            wr_en = 1;
            din = din + 1;
        end

        @(posedge clk);
        wr_en = 0;

        
        // Empty FIFO completely
        
        $display("\nEmptying FIFO...");
        repeat(DEPTH) begin
            @(posedge clk);
            rd_en = 1;
        end

        @(posedge clk);
        rd_en = 0;

        
        // Simultaneous Read & Write
        
        $display("\nSimultaneous Read and Write...");

        @(posedge clk);
        wr_en = 1;
        din = 8'hAA;

        @(posedge clk);
        wr_en = 0;

        @(posedge clk);
        wr_en = 1;
        rd_en = 1;
        din = 8'hBB;

        @(posedge clk);
        wr_en = 0;
        rd_en = 0;

        #20;
        $finish;
    end

    // Monitor signals
    initial begin
        $display("Time\tWr\tRd\tDin\tDout\tCount\tFull\tEmpty");
        $monitor("%0t\t%b\t%b\t%h\t%h\t%d\t%b\t%b",
                 $time,
                 wr_en,
                 rd_en,
                 din,
                 dout,
                 uut.count,
                 full,
                 empty);
    end

    initial begin
        $dumpfile("dump.vcd");   
        $dumpvars(0, tb_sync_fifo); 
    end

endmodule

simulation/dump.vcd
$date
	Wed Jul 15 23:31:36 2026
$end
$version
	Icarus Verilog
$end
$timescale
	1ps
$end
$scope module tb_sync_fifo $end
$var wire 1 ! full $end
$var wire 1 " empty $end
$var wire 8 # dout [7:0] $end
$var parameter 32 $ ADDR_WIDTH $end
$var parameter 32 % DATA_WIDTH $end
$var parameter 32 & DEPTH $end
$var reg 1 ' clk $end
$var reg 8 ( din [7:0] $end
$var reg 1 ) rd_en $end
$var reg 1 * rst $end
$var reg 1 + wr_en $end
$scope module uut $end
$var wire 1 ' clk $end
$var wire 8 , din [7:0] $end
$var wire 1 ) rd_en $end
$var wire 1 * rst $end
$var wire 1 + wr_en $end
$var wire 1 ! full $end
$var wire 1 " empty $end
$var parameter 32 - ADDR_WIDTH $end
$var parameter 32 . DATA_WIDTH $end
$var parameter 32 / DEPTH $end
$var reg 5 0 count [4:0] $end
$var reg 8 1 dout [7:0] $end
$var reg 4 2 rd_ptr [3:0] $end
$var reg 4 3 wr_ptr [3:0] $end
$upscope $end
$upscope $end
$enddefinitions $end
$comment Show the parameter values. $end
$dumpall
b10000 /
b1000 .
b100 -
b10000 &
b1000 %
b100 $
$end
#0
$dumpvars
b0 3
b0 2
b0 1
b0 0
b0 ,
0+
1*
0)
b0 (
0'
b0 #
1"
0!
$end
#5000
1'
#10000
0'
#15000
1'
#20000
0'
0*
#25000
0"
b1 0
b1 3
b10001 (
b10001 ,
1+
1'
#30000
0'
#35000
b10 3
b10 0
b100010 (
b100010 ,
1'
#40000
0'
#45000
b11 0
b11 3
b110011 (
b110011 ,
1'
#50000
0'
#55000
b100 3
b100 0
b1000100 (
b1000100 ,
1'
#60000
0'
#65000
b101 0
b101 3
b1010101 (
b1010101 ,
1'
#70000
0'
#75000
0+
1'
#80000
0'
#85000
b100 0
b1 2
b10001 #
b10001 1
1)
1'
#90000
0'
#95000
b10 2
b100010 #
b100010 1
b11 0
1'
#100000
0'
#105000
b10 0
b11 2
b110011 #
b110011 1
1'
#110000
0'
#115000
b100 2
b1000100 #
b1000100 1
b1 0
1'
#120000
0'
#125000
1"
b0 0
b101 2
b1010101 #
b1010101 1
1'
#130000
0'
#135000
0)
1'
#140000
0'
#145000
0"
b1 0
b110 3
b1010110 (
b1010110 ,
1+
1'
#150000
0'
#155000
b111 3
b10 0
b1010111 (
b1010111 ,
1'
#160000
0'
#165000
b11 0
b1000 3
b1011000 (
b1011000 ,
1'
#170000
0'
#175000
b1001 3
b100 0
b1011001 (
b1011001 ,
1'
#180000
0'
#185000
b101 0
b1010 3
b1011010 (
b1011010 ,
1'
#190000
0'
#195000
b1011 3
b110 0
b1011011 (
b1011011 ,
1'
#200000
0'
#205000
b111 0
b1100 3
b1011100 (
b1011100 ,
1'
#210000
0'
#215000
b1101 3
b1000 0
b1011101 (
b1011101 ,
1'
#220000
0'
#225000
b1001 0
b1110 3
b1011110 (
b1011110 ,
1'
#230000
0'
#235000
b1111 3
b1010 0
b1011111 (
b1011111 ,
1'
#240000
0'
#245000
b1011 0
b0 3
b1100000 (
b1100000 ,
1'
#250000
0'
#255000
b1 3
b1100 0
b1100001 (
b1100001 ,
1'
#260000
0'
#265000
b1101 0
b10 3
b1100010 (
b1100010 ,
1'
#270000
0'
#275000
b11 3
b1110 0
b1100011 (
b1100011 ,
1'
#280000
0'
#285000
b1111 0
b100 3
b1100100 (
b1100100 ,
1'
#290000
0'
#295000
b101 3
1!
b10000 0
b1100101 (
b1100101 ,
1'
#300000
0'
#305000
0+
1'
#310000
0'
#315000
b110 2
b1010110 #
b1010110 1
0!
b1111 0
1)
1'
#320000
0'
#325000
b1110 0
b111 2
b1010111 #
b1010111 1
1'
#330000
0'
#335000
b1000 2
b1011000 #
b1011000 1
b1101 0
1'
#340000
0'
#345000
b1100 0
b1001 2
b1011001 #
b1011001 1
1'
#350000
0'
#355000
b1010 2
b1011010 #
b1011010 1
b1011 0
1'
#360000
0'
#365000
b1010 0
b1011 2
b1011011 #
b1011011 1
1'
#370000
0'
#375000
b1100 2
b1011100 #
b1011100 1
b1001 0
1'
#380000
0'
#385000
b1000 0
b1101 2
b1011101 #
b1011101 1
1'
#390000
0'
#395000
b1110 2
b1011110 #
b1011110 1
b111 0
1'
#400000
0'
#405000
b110 0
b1111 2
b1011111 #
b1011111 1
1'
#410000
0'
#415000
b0 2
b1100000 #
b1100000 1
b101 0
1'
#420000
0'
#425000
b100 0
b1 2
b1100001 #
b1100001 1
1'
#430000
0'
#435000
b10 2
b1100010 #
b1100010 1
b11 0
1'
#440000
0'
#445000
b10 0
b11 2
b1100011 #
b1100011 1
1'
#450000
0'
#455000
b100 2
b1100100 #
b1100100 1
b1 0
1'
#460000
0'
#465000
1"
b0 0
b101 2
b1100101 #
b1100101 1
1'
#470000
0'
#475000
0)
1'
#480000
0'
#485000
0"
b1 0
b110 3
b10101010 (
b10101010 ,
1+
1'
#490000
0'
#495000
0+
1'
#500000
0'
#505000
b110 2
b10101010 #
b10101010 1
b111 3
b10111011 (
b10111011 ,
1)
1+
1'
#510000
0'
#515000
0)
0+
1'
